tkurses/__init__.py
tkurses/core.py
tkurses/layout.py
tkurses/settings.py
tkurses/themes.py
tkurses/widgets/__init__.py
tkurses/widgets/base.py
tkurses/widgets/button.py
tkurses/widgets/frame.py
tkurses/widgets/inputbox.py
tkurses/widgets/label.py
tkurses/widgets/textBox.py
tkurses-0.3.11.dist-info/METADATA
tkurses-0.3.11.dist-info/WHEEL
tkurses-0.3.11.dist-info/top_level.txt
tkurses-0.3.11.dist-info/RECORD
