Metadata-Version: 2.1
Name: tkurses
Version: 0.3.11
Summary: Tkinter-like themed UI framework for curses... New aditions to 0.3.1: proportional x,y,width,height
Home-page: https://not-aplicable.com
Author: Freeboardtortoise
Author-email: Freeboardtortoise@gmail.com
Requires-Python: >=3.6
